BaoFangRisk/__init__.py
BaoFangRisk/BFBarra/__init__.py
BaoFangRisk/BFBarra/base.py
BaoFangRisk/BFBarra/rq_barra.py
BaoFangRisk/BFData/__init__.py
BaoFangRisk/BFData/account.py
BaoFangRisk/BFData/base_datastruct.py
BaoFangRisk/BFData/portfolio.py
BaoFangRisk/BFFetch/__init__.py
BaoFangRisk/BFFetch/base.py
BaoFangRisk/BFFetch/rq_fetch.py
BaoFangRisk/BFOpt/__init__.py
BaoFangRisk/BFRisk/__init__.py
BaoFangRisk/BFRisk/baofang_risk.py
BaoFangRisk/BFUtil/__init__.py
BaoFangRisk/BFUtil/base.py
BaoFangRisk/BFUtil/code.py
BaoFangRisk/BFUtil/logs.py
BaoFangRisk-1.0.0.dist-info/LICENSE
BaoFangRisk-1.0.0.dist-info/METADATA
BaoFangRisk-1.0.0.dist-info/WHEEL
BaoFangRisk-1.0.0.dist-info/top_level.txt
BaoFangRisk-1.0.0.dist-info/zip-safe
BaoFangRisk-1.0.0.dist-info/RECORD
